qinglongsdk/__init__.py
qinglongsdk/ql.py
qinglongsdk/ql_config.py
qinglongsdk/ql_dependence.py
qinglongsdk/ql_env.py
qinglongsdk/ql_log.py
qinglongsdk/ql_script.py
qinglongsdk/ql_system.py
qinglongsdk/ql_task.py
qinglongsdk-0.1.6.dist-info/LICENSE
qinglongsdk-0.1.6.dist-info/METADATA
qinglongsdk-0.1.6.dist-info/WHEEL
qinglongsdk-0.1.6.dist-info/top_level.txt
qinglongsdk-0.1.6.dist-info/RECORD
