Metadata-Version: 2.1
Name: qinglongsdk
Version: 0.1.6
Summary: 青龙面板apiSDK
Home-page: https://github.com/yuxian158/qinglong-api
Author: Jxell
Author-email: 15717980@qq.com
Project-URL: Bug Tracker, https://github.com/yuxian158/qinglong-api/issues
Classifier: Programming Language :: Python :: 3
Classifier: License :: OSI Approved :: MIT License
Classifier: Operating System :: OS Independent
Requires-Python: >=3.6
License-File: LICENSE
Requires-Dist: requests
